[
  {
    "id": "bank-expense-20260501-_-400",
    "date": "2026-05-01",
    "merchant": "הפקדה לפקדון",
    "amount": 400,
    "charged_amount": 400,
    "currency": "ILS",
    "category": "transfers",
    "card": "bank",
    "source": "local",
    "type": "expense",
    "transaction_type": "regular",
    "reference": "2612185513387"
  },
  {
    "id": "bank-expense-20260503-_-375",
    "date": "2026-05-03",
    "merchant": "מקס איט פיננסי",
    "amount": 375,
    "charged_amount": 375,
    "currency": "ILS",
    "category": "fees",
    "card": "bank",
    "source": "local",
    "type": "expense",
    "transaction_type": "regular",
    "reference": "34685693"
  },
  {
    "id": "bank-rent-20260503-rent-7085",
    "date": "2026-05-03",
    "merchant": "שכר דירה",
    "amount": 7085,
    "charged_amount": 7085,
    "currency": "ILS",
    "category": "rent",
    "card": "bank",
    "source": "local",
    "type": "expense",
    "transaction_type": "regular",
    "reference": "10131"
  },
  {
    "id": "bank-expense-20260503-_-400",
    "date": "2026-05-03",
    "merchant": "שר נועה",
    "amount": 400,
    "charged_amount": 400,
    "currency": "ILS",
    "category": "transfers",
    "card": "bank",
    "source": "local",
    "type": "expense",
    "transaction_type": "regular",
    "reference": "456477727"
  },
  {
    "id": "bank-expense-20260508-_-7600",
    "date": "2026-05-08",
    "merchant": "\"גני שובבני\"  ציגלמן בטי",
    "amount": 7600,
    "charged_amount": 7600,
    "currency": "ILS",
    "category": "kids",
    "card": "bank",
    "source": "local",
    "type": "expense",
    "transaction_type": "regular",
    "reference": "457879992"
  },
  {
    "id": "bank-expense-20260508-_-9955.49",
    "date": "2026-05-08",
    "merchant": "חיסכון טיסה",
    "amount": 9955.49,
    "charged_amount": 9955.49,
    "currency": "ILS",
    "category": "other",
    "card": "bank",
    "source": "local",
    "type": "expense",
    "transaction_type": "regular",
    "reference": "10832"
  },
  {
    "id": "bank-expense-20260511-_-1298",
    "date": "2026-05-11",
    "merchant": "ירון סלע",
    "amount": 1298,
    "charged_amount": 1298,
    "currency": "ILS",
    "category": "transfers",
    "card": "bank",
    "source": "local",
    "type": "expense",
    "transaction_type": "regular",
    "reference": "458403808"
  },
  {
    "id": "bank-expense-20260515-_-400",
    "date": "2026-05-15",
    "merchant": "העברה יוצאת",
    "amount": 400,
    "charged_amount": 400,
    "currency": "ILS",
    "category": "transfers",
    "card": "bank",
    "source": "local",
    "type": "expense",
    "transaction_type": "regular",
    "reference": "459458124"
  },
  {
    "id": "bank-expense-20260515-_-380",
    "date": "2026-05-15",
    "merchant": "וועד בית",
    "amount": 380,
    "charged_amount": 380,
    "currency": "ILS",
    "category": "utilities",
    "card": "bank",
    "source": "local",
    "type": "expense",
    "transaction_type": "regular",
    "reference": "20730123777"
  }
]